PyLoadBar/__init__.py
PyLoadBar/main.py
PyLoadBar/tests/PyLoadBar_test.py
PyLoadBar/tests/__init__.py
PyLoadBar-0.2.0.dist-info/LICENSE
PyLoadBar-0.2.0.dist-info/METADATA
PyLoadBar-0.2.0.dist-info/WHEEL
PyLoadBar-0.2.0.dist-info/top_level.txt
PyLoadBar-0.2.0.dist-info/RECORD
