Metadata-Version: 2.1
Name: PyLoadBar
Version: 0.2.0
Summary: Customizeable loading sequence/progress bar generator, enabling users to customize start/finish messages, toggle sequence type, and set total iterations among other features.
Home-page: https://github.com/schlopp96/PyLoadBar
Author: schlopp96
Author-email: schloppdaddy@gmail.com
License: GPL v3.0
Keywords: python, load, bar, loading, sequence, progress, progress-bar, simple, easy, utilities, package, module, tqdm, pyloadbar, developer, tool
Platform: UNKNOWN
Classifier: Development Status :: 3 - Alpha
Classifier: Intended Audience :: Developers
Classifier: Intended Audience :: End Users/Desktop
Classifier: License :: OSI Approved :: GNU General Public License v3 (GPLv3)
Classifier: Natural Language :: English
Classifier: Operating System :: Microsoft :: Windows
Classifier: Programming Language :: Python :: 3
Classifier: Programming Language :: Python :: 3.9
Classifier: Programming Language :: Python :: 3.10
Classifier: Topic :: Utilities
License-File: LICENSE
Requires-Dist: setuptools (>=58.1.0)
Requires-Dist: tqdm (==4.64.0)
